wfst4str-1.0.4.dist-info/METADATA
wfst4str-1.0.4.dist-info/WHEEL
wfst4str/__init__.py
wfst4str/wfst4str.pyd
wfst4str-1.0.4.dist-info/RECORD
