Metadata-Version: 2.1
Name: wfst4str
Version: 1.0.4
Classifier: Programming Language :: Rust
Classifier: Operating System :: POSIX :: Linux
Summary: Python library based on rustfst for manipulatig strings with wFSTs
Keywords: fst,wfst,nlp,linguistics,python
Home-Page: https://github.com/dmort27/wfst4str
License: MIT
